KafkaUnity/__init__.py
KafkaUnity/unitykafka.py
KafkaUnity-1.0.0.dist-info/METADATA
KafkaUnity-1.0.0.dist-info/WHEEL
KafkaUnity-1.0.0.dist-info/top_level.txt
KafkaUnity-1.0.0.dist-info/RECORD
