Metadata-Version: 2.1
Name: KafkaUnity
Version: 1.0.0
Summary: API for Kafka Python
Home-page: UNKNOWN
Author: Jake Fogden
Author-email: jake.fogden@vodafone.com
License: UNKNOWN
Keywords: Kafka,Python,Unity
Platform: UNKNOWN
Classifier: Development Status :: 3 - Alpha
Classifier: Intended Audience :: Developers
Classifier: Programming Language :: Python :: 3
Classifier: Operating System :: MacOS :: MacOS X
Classifier: Operating System :: Microsoft :: Windows
Requires-Dist: kafka-python
